LICENSE
README.md
setup.py
nfmodelapis/__init__.py
nfmodelapis.egg-info/PKG-INFO
nfmodelapis.egg-info/SOURCES.txt
nfmodelapis.egg-info/dependency_links.txt
nfmodelapis.egg-info/requires.txt
nfmodelapis.egg-info/top_level.txt
nfmodelapis/text/__init__.py
nfmodelapis/text/SentenceEmbedder/__init__.py
nfmodelapis/text/SentenceEmbedder/model_select.py
nfmodelapis/text/SentenceEmbedder/contrastive_tension/__init__.py
nfmodelapis/text/SentenceEmbedder/contrastive_tension/ct.py
nfmodelapis/text/SentenceEmbedder/simcse/__init__.py
nfmodelapis/text/SentenceEmbedder/simcse/simcse.py
nfmodelapis/text/SentenceEmbedder/tsdae/__init__.py
nfmodelapis/text/SentenceEmbedder/tsdae/tsdae.py
nfmodelapis/text/ner/__init__.py
nfmodelapis/text/ner/pipeline.py
nfmodelapis/text/question_answering/__init__.py
nfmodelapis/text/question_answering/pipeline.py
nfmodelapis/text/summarization/__init__.py
nfmodelapis/text/summarization/pipeline.py