Metadata-Version: 2.1
Name: nfmodelapis
Version: 0.0.2
Summary: Data Curation over Time
Home-page: https://github.com/nfflow/nfmodelapis
Author: Abhijith Neil Abraham
Author-email: abhijithneilabrahampk@gmail.com
License: MIT License
Requires-Python: >=3.6
Provides-Extra: qa
Provides-Extra: summarization
Provides-Extra: unsupervised
Provides-Extra: all
License-File: LICENSE
